indianl_nlp/__init__.py
indianl_nlp/generate_text.py
indianlang_nlp-0.0.1.5.dist-info/METADATA
indianlang_nlp-0.0.1.5.dist-info/WHEEL
indianlang_nlp-0.0.1.5.dist-info/top_level.txt
indianlang_nlp-0.0.1.5.dist-info/RECORD
