Metadata-Version: 2.1
Name: indianlang-nlp
Version: 0.0.1.5
Home-page: https://github.com/panditamey/indianlang-nlp
Author: Amey Pandit
Requires-Dist: keras
Requires-Dist: tensorflow
Requires-Dist: gdown
